dynamicalsystem/gazette/__init__.py
dynamicalsystem/gazette/__main__.py
dynamicalsystem/gazette/content.py
dynamicalsystem/gazette/hello.py
dynamicalsystem/gazette/publishers.py
dynamicalsystem/gazette/review.py
dynamicalsystem/gazette/watermarks.py
dynamicalsystem_gazette-0.1.5.dist-info/METADATA
dynamicalsystem_gazette-0.1.5.dist-info/WHEEL
dynamicalsystem_gazette-0.1.5.dist-info/entry_points.txt
dynamicalsystem_gazette-0.1.5.dist-info/RECORD
