Metadata-Version: 2.4
Name: dynamicalsystem.gazette
Version: 0.1.5
Summary: POSSE Publisher
Author-email: Simon Horrobin <simon@dynamicalsystem.com>
Classifier: Development Status :: 3 - Alpha
Classifier: Intended Audience :: Developers
Classifier: License :: OSI Approved :: MIT License
Classifier: Topic :: Software Development :: Libraries :: Python Modules
Requires-Python: >=3.13
Requires-Dist: atproto>=0.0.56
Requires-Dist: dynamicalsystem-halogen>=0.1.2
Requires-Dist: requests>=2.32.3
